funcnodes_hplc/__init__.py
funcnodes_hplc/hplc_run.py
funcnodes_hplc/report.py
funcnodes_hplc/signals.py
funcnodes_hplc-0.1.1.dist-info/METADATA
funcnodes_hplc-0.1.1.dist-info/WHEEL
funcnodes_hplc-0.1.1.dist-info/entry_points.txt
funcnodes_hplc-0.1.1.dist-info/RECORD
