Metadata-Version: 2.1
Name: funcnodes-hplc
Version: 0.1.1
Summary: 
License: MIT
Author: Julian Kimmig
Author-email: julian.kimmig@linkdlab.de
Requires-Python: >=3.11
Classifier: License :: OSI Approved :: MIT License
Classifier: Programming Language :: Python :: 3
Classifier: Programming Language :: Python :: 3.11
Classifier: Programming Language :: Python :: 3.12
Classifier: Programming Language :: Python :: 3.13
Requires-Dist: funcnodes
Requires-Dist: funcnodes-pandas (>=0.2.6)
Requires-Dist: funcnodes-plotly
Requires-Dist: funcnodes-span (>=0.3.1)
Requires-Dist: llvmlite (>=0.4)
Requires-Dist: numba (>=0.5)
Requires-Dist: scipy (>=1.14)
Project-URL: download, https://pypi.org/project/funcnodes-hplc/#files
Project-URL: homepage, https://github.com/Linkdlab/funcnodes_hplc
Project-URL: source, https://github.com/Linkdlab/funcnodes_hplc
Project-URL: tracker, https://github.com/Linkdlab/funcnodes_hplc/issues
